{
  "frames": {
    "MagicBurstParticle.png": {
      "frame": {
        "x": 0,
        "y": 0,
        "w": 353,
        "h": 1559
      },
      "rotated": false,
      "trimmed": true,
      "spriteSourceSize": {
        "x": 0,
        "y": 50,
        "w": 353,
        "h": 1559
      },
      "sourceSize": {
        "w": 353,
        "h": 1620
      },
      "pivot": {
        "x": 0.5,
        "y": 0.5
      }
    },
    "SmokeParticle.png": {
      "frame": {
        "x": 0,
        "y": 1559,
        "w": 80,
        "h": 218
      },
      "rotated": false,
      "trimmed": true,
      "spriteSourceSize": {
        "x": 0,
        "y": 0,
        "w": 80,
        "h": 218
      },
      "sourceSize": {
        "w": 125,
        "h": 218
      },
      "pivot": {
        "x": 0.5,
        "y": 0.5
      }
    },
    "HollowCircle.png": {
      "frame": {
        "x": 0,
        "y": 1777,
        "w": 156,
        "h": 156
      },
      "rotated": false,
      "trimmed": false,
      "spriteSourceSize": {
        "x": 0,
        "y": 0,
        "w": 156,
        "h": 156
      },
      "sourceSize": {
        "w": 156,
        "h": 156
      },
      "pivot": {
        "x": 0.5,
        "y": 0.5
      }
    },
    "BasicMetaballCircle.png": {
      "frame": {
        "x": 0,
        "y": 1933,
        "w": 100,
        "h": 100
      },
      "rotated": false,
      "trimmed": false,
      "spriteSourceSize": {
        "x": 0,
        "y": 0,
        "w": 100,
        "h": 100
      },
      "sourceSize": {
        "w": 100,
        "h": 100
      },
      "pivot": {
        "x": 0.5,
        "y": 0.5
      }
    },
    "Pixel.png": {
      "frame": {
        "x": 0,
        "y": 2033,
        "w": 2,
        "h": 2
      },
      "rotated": false,
      "trimmed": false,
      "spriteSourceSize": {
        "x": 0,
        "y": 0,
        "w": 2,
        "h": 2
      },
      "sourceSize": {
        "w": 2,
        "h": 2
      },
      "pivot": {
        "x": 0.5,
        "y": 0.5
      }
    },
    "ElectricSparkParticle.png": {
      "frame": {
        "x": 353,
        "y": 0,
        "w": 125,
        "h": 500
      },
      "rotated": false,
      "trimmed": false,
      "spriteSourceSize": {
        "x": 0,
        "y": 0,
        "w": 125,
        "h": 500
      },
      "sourceSize": {
        "w": 125,
        "h": 500
      },
      "pivot": {
        "x": 0.5,
        "y": 0.5
      }
    }
  },
  "meta": {
    "app": "http://free-tex-packer.com",
    "version": "0.6.7",
    "image": "texture.png",
    "format": "RGBA8888",
    "size": {
      "w": 478,
      "h": 2035
    },
    "scale": 1
  }
}